jedidebug/__init__.py
jedidebug/core.py
jedidebug/handlers.py
jedidebug/quotes.py
jedidebug-0.2.0.dist-info/licenses/LICENSE
tests/__init__.py
tests/test_jedidebug.py
jedidebug-0.2.0.dist-info/METADATA
jedidebug-0.2.0.dist-info/WHEEL
jedidebug-0.2.0.dist-info/top_level.txt
jedidebug-0.2.0.dist-info/RECORD
