Metadata-Version: 2.4
Name: jedidebug
Version: 0.2.0
Summary: A library that motivates programmers with Star Wars quotes when their code has bugs
Home-page: https://github.com/notarealprogrammer001/jedidebug
Author: Not a Real Programmer
Author-email: Not a Real Programmer <notarealprogrammer010@gmail.com>
License: MIT
Project-URL: Homepage, https://github.com/notarealprogrammer001/jedidebug
Project-URL: Bug Tracker, https://github.com/notarealprogrammer001/jedidebug/issues
Keywords: star wars,jedi,error,exception,debug,motivational
Classifier: Development Status :: 4 - Beta
Classifier: Intended Audience :: Developers
Classifier: License :: OSI Approved :: MIT License
Classifier: Programming Language :: Python :: 3
Classifier: Programming Language :: Python :: 3.6
Classifier: Programming Language :: Python :: 3.7
Classifier: Programming Language :: Python :: 3.8
Classifier: Programming Language :: Python :: 3.9
Classifier: Programming Language :: Python :: 3.10
Classifier: Programming Language :: Python :: 3.11
Classifier: Topic :: Software Development :: Libraries :: Python Modules
Classifier: Topic :: Software Development :: Debuggers
Classifier: Topic :: Utilities
Requires-Python: >=3.6
License-File: LICENSE
Dynamic: author
Dynamic: home-page
Dynamic: license-file
Dynamic: requires-python
